cimageio/png.py
cimageio/libcimageio.so
cimageio/__init__.py
cimageio/jpeg.py
cimageio/_common.py
cimageio-0.1.0.dist-info/METADATA
cimageio-0.1.0.dist-info/WHEEL
cimageio-0.1.0.dist-info/RECORD
cimageio-0.1.0.dist-info/top_level.txt
